mp_telegram_bot/__init__.py
mp_telegram_bot/_version.py
mp_telegram_bot/config.py
mp_telegram_bot/mp_telegram_bot.py
mp_telegram_bot/duet/__init__.py
mp_telegram_bot/duet/api.py
mp_telegram_bot-0.0.1.data/data/mp_telegram_bot.service
mp_telegram_bot-0.0.1.dist-info/LICENSE
mp_telegram_bot-0.0.1.dist-info/METADATA
mp_telegram_bot-0.0.1.dist-info/WHEEL
mp_telegram_bot-0.0.1.dist-info/entry_points.txt
mp_telegram_bot-0.0.1.dist-info/top_level.txt
mp_telegram_bot-0.0.1.dist-info/RECORD
