Metadata-Version: 2.1
Name: mp-telegram-bot
Version: 0.0.1
Summary: Python Telegram Bot for Meltingplot 3D Printers.
Home-page: UNKNOWN
Author: Tim Schneider
Author-email: tim@meltingplot.net
License: Apache License
Platform: UNKNOWN
License-File: LICENSE
Requires-Dist: python-telegram-bot
Requires-Dist: requests
Requires-Dist: attrs
Requires-Dist: imageio[ffmpeg]
Provides-Extra: test
Requires-Dist: pytest-cov ; extra == 'test'
Requires-Dist: pytest-mock ; extra == 'test'
Requires-Dist: flake8 ; extra == 'test'
Requires-Dist: flake8-import-order ; extra == 'test'
Requires-Dist: flake8-blind-except ; extra == 'test'
Requires-Dist: flake8-builtins ; extra == 'test'
Requires-Dist: flake8-docstrings ; extra == 'test'
Requires-Dist: flake8-bugbear ; extra == 'test'
Requires-Dist: flake8-comprehensions ; extra == 'test'
Requires-Dist: flake8-commas ; extra == 'test'
Requires-Dist: pep8-naming ; extra == 'test'
Requires-Dist: bandit ; extra == 'test'
Requires-Dist: yapf ; extra == 'test'
